{
  "project_info": {
    "project_number": "119643993095",
    "project_id": "mentalbloom-app-firebase",
    "storage_bucket": "mentalbloom-app-firebase.firebasestorage.app"
  },
  "client": [
    {
      "client_info": {
        "mobilesdk_app_id": "1:119643993095:android:34e1611d46a8b2c2f626a2",
        "android_client_info": {
          "package_name": "com.example.mentalbloom"
        }
      },
      "oauth_client": [],
      "api_key": [
        {
          "current_key": "AIzaSyDRI-EOlDhBzCh3chzsrssO_UzrwD6cU3U"
        }
      ],
      "services": {
        "appinvite_service": {
          "other_platform_oauth_client": []
        }
      } 
    }
  ],
  "configuration_version": "1"
}